netbox_vlan_manager/__init__.py
netbox_vlan_manager/forms.py
netbox_vlan_manager/models.py
netbox_vlan_manager/navigation.py
netbox_vlan_manager/tables.py
netbox_vlan_manager/urls.py
netbox_vlan_manager/version.py
netbox_vlan_manager/views.py
netbox_vlan_manager/api/__init__.py
netbox_vlan_manager/api/serializers.py
netbox_vlan_manager/api/urls.py
netbox_vlan_manager/api/views.py
netbox_vlan_manager/migrations/0001_initial.py
netbox_vlan_manager/migrations/__init__.py
netbox_vlan_manager/templates/netbox_vlan_manager/vlangroupset.html
netbox_vlan_manager/templates/netbox_vlan_manager/vlangroupset_vlans.html
netbox_vlan_manager/templates/netbox_vlan_manager/inc/toggle_available.html
netbox_vlan_manager/templatetags/__init__.py
netbox_vlan_manager/templatetags/view_helpers.py
netbox_vlan_manager-0.2.0.dist-info/LICENSE
netbox_vlan_manager-0.2.0.dist-info/METADATA
netbox_vlan_manager-0.2.0.dist-info/WHEEL
netbox_vlan_manager-0.2.0.dist-info/top_level.txt
netbox_vlan_manager-0.2.0.dist-info/RECORD
