Metadata-Version: 2.1
Name: netbox-vlan-manager
Version: 0.2.0
Summary: VLAN Manager for multiple VLAN Groups
Home-page: https://github.com/miyuk/netbox-vlan-manager/
Author: miyuk
Author-email: miyuk@miyuk.net
Classifier: Development Status :: 4 - Beta
Classifier: Framework :: Django
Classifier: Programming Language :: Python :: 3
License-File: LICENSE
